rocketserializer/__init__.py
rocketserializer/_helpers.py
rocketserializer/cli.py
rocketserializer/nb_builder.py
rocketserializer/ork_extractor.py
rocketserializer/components/__init__.py
rocketserializer/components/drag_curve.py
rocketserializer/components/environment.py
rocketserializer/components/fins.py
rocketserializer/components/flight.py
rocketserializer/components/id.py
rocketserializer/components/motor.py
rocketserializer/components/nose_cone.py
rocketserializer/components/open_rocket_wrangler.py
rocketserializer/components/parachute.py
rocketserializer/components/rail_buttons.py
rocketserializer/components/rocket.py
rocketserializer/components/stored_results.py
rocketserializer/components/transition.py
rocketserializer-0.2.0.dist-info/LICENSE.md
rocketserializer-0.2.0.dist-info/METADATA
rocketserializer-0.2.0.dist-info/WHEEL
rocketserializer-0.2.0.dist-info/entry_points.txt
rocketserializer-0.2.0.dist-info/top_level.txt
rocketserializer-0.2.0.dist-info/RECORD
