Metadata-Version: 2.1
Name: rocketserializer
Version: 0.2.0
Summary: Easily convert your OpenRocket files into RocketPy simulations.
Author-email: Guilherme Fernandes <guilherme_fernandes@usp.br>, Patrick Sampaio <patricksampaio@usp.br>, Julio Machado <julioromac@outlook.com>
Maintainer-email: RocketPy Team <rocketpyteam@gmail.com>
License: MIT License
Project-URL: Documentation, https://docs.rocketpy.org/en/latest/
Project-URL: Repository, https://github.com/RocketPy-Team/RocketSerializer
Project-URL: Issues, https://github.com/RocketPy-Team/RocketSerializer/issues
Keywords: python,simulation,aerospace,motor,flight-simulator,trajectory,trajectory-simulator,rocket-simulator,openrocket,rocket-simulation
Classifier: Programming Language :: Python :: 3.8
Classifier: Programming Language :: Python :: 3.9
Classifier: Programming Language :: Python :: 3.10
Classifier: Programming Language :: Python :: 3.11
Classifier: Programming Language :: Python :: 3.12
Requires-Python: >=3.8
License-File: LICENSE.md
Requires-Dist: bs4
Requires-Dist: click >=8.0.0
Requires-Dist: lxml
Requires-Dist: numpy
Requires-Dist: orhelper ==0.1.3
Requires-Dist: pyyaml
Requires-Dist: rocketpy >=1.1.0
Requires-Dist: nbformat >=5.2.0
